flat_file_gdpr_anonymiser/__init__.py
flat_file_gdpr_anonymiser/__main__.py
flat_file_gdpr_anonymiser-0.1.2.dist-info/LICENSE
flat_file_gdpr_anonymiser-0.1.2.dist-info/METADATA
flat_file_gdpr_anonymiser-0.1.2.dist-info/WHEEL
flat_file_gdpr_anonymiser-0.1.2.dist-info/top_level.txt
flat_file_gdpr_anonymiser-0.1.2.dist-info/RECORD
