Metadata-Version: 2.1
Name: flat-file-gdpr-anonymiser
Version: 0.1.2
Summary: Flat File GDPR Anonymiser anonymises data in any input file using an encoding key and informed consent list.
Home-page: https://github.com/yForecasting/grafton
Author: Yves R. Sagaert
Author-email: yves.r.sagaert@pm.me
License: GNU GPLv3
Platform: UNKNOWN
Classifier: Development Status :: 7 - Inactive
Classifier: License :: OSI Approved :: GNU General Public License v3 (GPLv3)
Classifier: Programming Language :: Python
Classifier: Programming Language :: Python :: 3.5
Classifier: Programming Language :: Python :: 3.6
Classifier: Topic :: Software Development :: Libraries
Classifier: Topic :: Software Development :: Libraries :: Python Modules
Classifier: Intended Audience :: Developers
Requires-Python: >=3.5
License-File: LICENSE
